{"node_id":"kg_pattern_识别技术术语歧义_同音_相似词_并提供双重解释","version":"5ff0d2589b3922ff6dcc0a491540aa0199e734ba4ef01ef5b4901e2e69097016","parents":[],"timestamp":1773124125,"content":{"title":"Behavior Pattern","body":"# Behavior Pattern\n\n识别技术术语歧义（同音/相似词）并提供双重解释\n\n## Summary\n\n识别技术术语歧义（同音/相似词）并提供双重解释...\n\n## Updated at\n\n2026-03-10T06:28:45.238Z\n\n## Type\n\nbehavior_pattern","structured_data":{"content_type":"markdown","kb.last_agent_id":"mempedia-codecli","kb.last_reason":"Behavior pattern extraction","kb.last_source":"kg_pattern","kb.updated_at":"1773124125"},"links":[],"highlights":["Behavior Pattern","Summary","Updated at","Type"]},"confidence":0.9,"importance":2.0}