{"node_id":"kg_atomic_react_前端框架","version":"729478e829ff375ab9f680ee2e13e2256b5ee14466f496782814b74ea951adb7","parents":[],"timestamp":1773124125,"content":{"title":"React (前端框架)","body":"# React (前端框架)\n\n## Summary\n\nMeta(Facebook)开发的用于构建UI的JavaScript库\n\n## Details\n\n核心特性包括：1)组件化架构（可复用的独立UI单元）；2)虚拟DOM（Diff算法提升渲染性能）；3)JSX语法（JS中嵌入类HTML标记）；4)单向数据流（可预测的状态管理）。由Meta维护，需配合Babel、Webpack等工具链使用，是当前主流前端技术栈核心。\n\n## Updated at\n\n2026-03-10T06:28:45.238Z\n\n## Type\n\natomic_knowledge","structured_data":{"content_type":"markdown","kb.last_agent_id":"mempedia-codecli","kb.last_reason":"Atomic knowledge update","kb.last_source":"kg_atomic","kb.updated_at":"1773124125"},"links":[],"highlights":["React (前端框架)","Summary","Details","Updated at","Type"]},"confidence":0.98,"importance":1.9}